[
    {
        "code": "KBU",
        "long": "69.1347",
        "lat": "34.5151",
        "elevation": "1820",
        "name": "GEOFON Station Kabul",
        "channels": []
    },
    {
        "code": "LHMI",
        "long": "96.9472",
        "lat": "5.2288",
        "elevation": "3",
        "name": "GEOFON Station Lhokseumave",
        "channels": []
    },
    {
        "code": "MNAI",
        "long": "102.9557",
        "lat": "-4.3605",
        "elevation": "154",
        "name": "GEOFON Station Manna",
        "channels": []
    },
    {
        "code": "MALT",
        "long": "38.4273",
        "lat": "38.3134",
        "elevation": "1120",
        "name": "Malatya",
        "channels": []
    },
    {
        "code": "HMDM",
        "long": "73.1822",
        "lat": "6.7731",
        "elevation": "1",
        "name": "GEOFON Station Hanimaadhoo",
        "channels": []
    },
    {
        "code": "WLF",
        "long": "6.1526",
        "lat": "49.6646",
        "elevation": "295",
        "name": "Walferdange",
        "channels": []
    },
    {
        "code": "MAUI",
        "long": "-156.2448",
        "lat": "20.7668",
        "elevation": "2060",
        "name": "Haleakala",
        "channels": []
    },
    {
        "code": "GHAJ",
        "long": "35.5665",
        "lat": "31.3034",
        "elevation": "-58",
        "name": "GEOFON",
        "channels": []
    },
    {
        "code": "MHV",
        "long": "37.7664",
        "lat": "54.9595",
        "elevation": "150",
        "name": "Michnevo",
        "channels": []
    },
    {
        "code": "BGIO",
        "long": "35.0877",
        "lat": "31.7219",
        "elevation": "752",
        "name": "Bar Giyyora",
        "channels": []
    },
    {
        "code": "CART",
        "long": "-1.0012",
        "lat": "37.5868",
        "elevation": "65",
        "name": "Cartagena",
        "channels": []
    },
    {
        "code": "ILTH",
        "long": "-6.3362",
        "lat": "54.0279",
        "elevation": "21",
        "name": "Belurgan, Co Louth",
        "channels": []
    },
    {
        "code": "STU",
        "long": "9.195",
        "lat": "48.7719",
        "elevation": "360",
        "name": "Stuttgart",
        "channels": []
    },
    {
        "code": "TNTI",
        "long": "127.3667",
        "lat": "0.7718",
        "elevation": "43",
        "name": "GEOFON Station Ternate",
        "channels": []
    },
    {
        "code": "APEZ",
        "long": "24.8859",
        "lat": "34.9777",
        "elevation": "435",
        "name": "Moni Apezanon",
        "channels": []
    },
    {
        "code": "HALK",
        "long": "80.6806",
        "lat": "6.0877",
        "elevation": "120",
        "name": "Hakmana",
        "channels": []
    },
    {
        "code": "MALK",
        "long": "80.5425",
        "lat": "8.3968",
        "elevation": "113",
        "name": "Mahakanadarawa",
        "channels": []
    },
    {
        "code": "PLAI",
        "long": "117.7765",
        "lat": "-8.8275",
        "elevation": "125",
        "name": "Plampang, Sumbawa",
        "channels": []
    },
    {
        "code": "SANT",
        "long": "25.4593",
        "lat": "36.3705",
        "elevation": "591",
        "name": "Santorini",
        "channels": []
    },
    {
        "code": "PMBI",
        "long": "104.6993",
        "lat": "-2.9024",
        "elevation": "25",
        "name": "Palembang",
        "channels": []
    },
    {
        "code": "RUE",
        "long": "13.78",
        "lat": "52.4759",
        "elevation": "40",
        "name": "Ruedersdorf",
        "channels": []
    },
    {
        "code": "NPW",
        "long": "96.1376",
        "lat": "19.7785",
        "elevation": "158",
        "name": "Naypyitaw",
        "channels": []
    },
    {
        "code": "DAMY",
        "long": "44.3869",
        "lat": "14.5613",
        "elevation": "2488",
        "name": "GEOFON Station Dhamar",
        "channels": []
    },
    {
        "code": "SOEI",
        "long": "124.2672",
        "lat": "-9.7553",
        "elevation": "1047",
        "name": "GEOFON Station Soe",
        "channels": []
    },
    {
        "code": "LODK",
        "long": "35.3616",
        "lat": "3.4219",
        "elevation": "665",
        "name": "Lodwar",
        "channels": []
    },
    {
        "code": "KARN",
        "long": "23.9174",
        "lat": "35.4019",
        "elevation": "420",
        "name": "Karanos",
        "channels": []
    },
    {
        "code": "PUL",
        "long": "30.317",
        "lat": "59.767",
        "elevation": "65",
        "name": "Pulkovo",
        "channels": []
    },
    {
        "code": "VAL",
        "long": "-10.2442",
        "lat": "51.9394",
        "elevation": "14",
        "name": "Valentia",
        "channels": []
    },
    {
        "code": "VOI",
        "long": "46.7933",
        "lat": "-21.9065",
        "elevation": "1158",
        "name": "Vohitsoka",
        "channels": []
    },
    {
        "code": "KARP",
        "long": "27.1611",
        "lat": "35.5471",
        "elevation": "524",
        "name": "Karpathos,Greece",
        "channels": []
    }
]